<?xml version="1.0" encoding="utf-8"?>
<?xml-stylesheet type="text/xsl" href="fval.xsl"?>
<FontValidatorReport RunDateTime="22 December 2019 01:31" MachineName="hintak-System-P">
<FontFile FileName="TlwgTypist-BoldOblique.otf" FileNameAndPath="z://usr/share/fonts/opentype/tlwg/TlwgTypist-BoldOblique.otf">
<Report ErrorType="I" ErrorCode="I0004" Message="The file begins with an Offset Table (file contains a single font)" />
<Font FontIndex="0">
<FontInfo FontName="Tlwg Typist Bold Oblique" FontVersion="Version 003.001 " FontDate="29/10/2018" />
<Report ErrorType="P" ErrorCode="P0011" Message="The numTables field is non-zero" Details="13" TestName="_OFFSET_numTables" />
<Report ErrorType="P" ErrorCode="P0010" Message="The searchRange, entrySelector, and rangeShift fields are all valid" TestName="_OFFSET_BinarySearchFields" />
<Report ErrorType="P" ErrorCode="P0032" Message="The directory entry tags are in ascending order" />
<Report ErrorType="P" ErrorCode="P0031" Message="The directory entry tag names are valid" />
<Report ErrorType="P" ErrorCode="P0030" Message="The directory entry table offsets are all multiples of 4" />
<Report ErrorType="P" ErrorCode="P0020" Message="All required tables are present" />
<Report ErrorType="W" ErrorCode="W0022" Message="Recommended table is missing" Details="DSIG" />
<Report ErrorType="P" ErrorCode="P0022" Message="No unnecessary tables are present" />
<Report ErrorType="P" ErrorCode="P0021" Message="Tables are in optimal order" />
<TableEntry Tag="CFF " Offset="0x00001b18" Length="0x000098ca" Checksum="0x1b8fb4c0" CodeFriendlyTag="CFF_">
<Report ErrorType="I" ErrorCode="I0041" Message="Table not selected for validation" />
</TableEntry>
<TableEntry Tag="FFTM" Offset="0x0000c5c8" Length="0x0000001c" Checksum="0x6ed2f79d" CodeFriendlyTag="FFTM">
<Report ErrorType="I" ErrorCode="I0040" Message="Not an OpenType table, contents not validated" Details="" />
</TableEntry>
<TableEntry Tag="GDEF" Offset="0x0000b3e4" Length="0x00000074" Checksum="0x0ecb0ffb" CodeFriendlyTag="GDEF">
<Report ErrorType="I" ErrorCode="I0041" Message="Table not selected for validation" />
</TableEntry>
<TableEntry Tag="GPOS" Offset="0x0000c0ac" Length="0x0000051a" Checksum="0x09ed08c5" CodeFriendlyTag="GPOS">
<Report ErrorType="I" ErrorCode="I0041" Message="Table not selected for validation" />
</TableEntry>
<TableEntry Tag="GSUB" Offset="0x0000b458" Length="0x00000c52" Checksum="0xdd1e214a" CodeFriendlyTag="GSUB">
<Report ErrorType="I" ErrorCode="I0041" Message="Table not selected for validation" />
</TableEntry>
<TableEntry Tag="OS/2" Offset="0x00000140" Length="0x00000060" Checksum="0x7b0b309e" CodeFriendlyTag="OS_2">
<Report ErrorType="I" ErrorCode="I0041" Message="Table not selected for validation" />
</TableEntry>
<TableEntry Tag="cmap" Offset="0x00001818" Length="0x000002de" Checksum="0xdf98a5a7" CodeFriendlyTag="cmap">
<Report ErrorType="I" ErrorCode="I0041" Message="Table not selected for validation" />
</TableEntry>
<TableEntry Tag="head" Offset="0x000000dc" Length="0x00000036" Checksum="0xfe7af51a" CodeFriendlyTag="head">
<Report ErrorType="I" ErrorCode="I0041" Message="Table not selected for validation" />
</TableEntry>
<TableEntry Tag="hhea" Offset="0x00000114" Length="0x00000024" Checksum="0x0879067b" CodeFriendlyTag="hhea">
<Report ErrorType="I" ErrorCode="I0041" Message="Table not selected for validation" />
</TableEntry>
<TableEntry Tag="hmtx" Offset="0x0000c5e4" Length="0x00000584" Checksum="0xd4ba3eb0" CodeFriendlyTag="hmtx">
<Report ErrorType="I" ErrorCode="I0041" Message="Table not selected for validation" />
</TableEntry>
<TableEntry Tag="maxp" Offset="0x00000138" Length="0x00000006" Checksum="0x01615000" CodeFriendlyTag="maxp">
<Report ErrorType="I" ErrorCode="I0041" Message="Table not selected for validation" />
</TableEntry>
<TableEntry Tag="name" Offset="0x000001a0" Length="0x00001678" Checksum="0xac83c378" CodeFriendlyTag="name">
<Report ErrorType="I" ErrorCode="I0041" Message="Table not selected for validation" />
</TableEntry>
<TableEntry Tag="post" Offset="0x00001af8" Length="0x00000020" Checksum="0xff7a0032" CodeFriendlyTag="post">
<Report ErrorType="I" ErrorCode="I0041" Message="Table not selected for validation" />
</TableEntry>
<RasterizationTest_BW>
<Report ErrorType="I" ErrorCode="I6059" Message="Could not perform rasterization" Details="Font has PostScript outlines, rasterization not yet implemented" />
</RasterizationTest_BW>
<RasterizationTest_Grayscale>
<Report ErrorType="I" ErrorCode="I0052" Message="Rasterization not selected for validation" />
</RasterizationTest_Grayscale>
<RasterizationTest_ClearType>
<Report ErrorType="I" ErrorCode="I0052" Message="Rasterization not selected for validation" />
</RasterizationTest_ClearType>
</Font>
<Report ErrorType="I" ErrorCode="I0005" Message="Total time validating file" Details="0:00:00" />
</FontFile>
</FontValidatorReport>
