<?xml version="1.0" encoding="utf-8"?>
<?xml-stylesheet type="text/xsl" href="fval.xsl"?>
<FontValidatorReport RunDateTime="25 March 2019 18:44" MachineName="hintak-System-P">
<FontFile FileName="Times_New_Roman.ttf" FileNameAndPath="z://usr/share/fonts/truetype/msttcorefonts/Times_New_Roman.ttf">
<Report ErrorType="I" ErrorCode="I0004" Message="The file begins with an Offset Table (file contains a single font)" />
<Font FontIndex="0">
<FontInfo FontName="Times New Roman" FontVersion="Version 2.82" FontDate="09/05/2000" />
<Report ErrorType="P" ErrorCode="P0011" Message="The numTables field is non-zero" Details="23" TestName="_OFFSET_numTables" />
<Report ErrorType="P" ErrorCode="P0010" Message="The searchRange, entrySelector, and rangeShift fields are all valid" TestName="_OFFSET_BinarySearchFields" />
<Report ErrorType="P" ErrorCode="P0032" Message="The directory entry tags are in ascending order" />
<Report ErrorType="P" ErrorCode="P0031" Message="The directory entry tag names are valid" />
<Report ErrorType="P" ErrorCode="P0030" Message="The directory entry table offsets are all multiples of 4" />
<Report ErrorType="P" ErrorCode="P0020" Message="All required tables are present" />
<Report ErrorType="P" ErrorCode="P0023" Message="All recommended tables are present" />
<Report ErrorType="W" ErrorCode="W0021" Message="Table is unnecessary" Details="PCLT table not needed, Microsoft no longer recommends including this table" />
<Report ErrorType="W" ErrorCode="W0020" Message="Tables are not in optimal order" Details="table 'LTSH' precedes table 'hmtx'" />
<TableEntry Tag="DSIG" Offset="0x0004f4ec" Length="0x000015c0" Checksum="0x1eeb9e1b" CodeFriendlyTag="DSIG">
<Report ErrorType="I" ErrorCode="I0041" Message="Table not selected for validation" />
</TableEntry>
<TableEntry Tag="GDEF" Offset="0x0004f150" Length="0x0000009a" Checksum="0x514451bc" CodeFriendlyTag="GDEF">
<Report ErrorType="I" ErrorCode="I0041" Message="Table not selected for validation" />
</TableEntry>
<TableEntry Tag="GSUB" Offset="0x0004f1ec" Length="0x000002de" Checksum="0xc8f7ad5b" CodeFriendlyTag="GSUB">
<Report ErrorType="I" ErrorCode="I0041" Message="Table not selected for validation" />
</TableEntry>
<TableEntry Tag="JSTF" Offset="0x0004f4cc" Length="0x0000001e" Checksum="0x6d2a6906" CodeFriendlyTag="JSTF">
<Report ErrorType="I" ErrorCode="I0041" Message="Table not selected for validation" />
</TableEntry>
<TableEntry Tag="LTSH" Offset="0x00004710" Length="0x0000052c" Checksum="0xba874f11" CodeFriendlyTag="LTSH">
<Report ErrorType="I" ErrorCode="I0041" Message="Table not selected for validation" />
</TableEntry>
<TableEntry Tag="OS/2" Offset="0x000001f8" Length="0x00000056" Checksum="0x10732def" CodeFriendlyTag="OS_2">
<Report ErrorType="I" ErrorCode="I0041" Message="Table not selected for validation" />
</TableEntry>
<TableEntry Tag="PCLT" Offset="0x0004f118" Length="0x00000036" Checksum="0x59d381e3" CodeFriendlyTag="PCLT">
<Report ErrorType="I" ErrorCode="I0041" Message="Table not selected for validation" />
</TableEntry>
<TableEntry Tag="VDMX" Offset="0x00004c3c" Length="0x00001194" Checksum="0x4e236882" CodeFriendlyTag="VDMX">
<Report ErrorType="I" ErrorCode="I0041" Message="Table not selected for validation" />
</TableEntry>
<TableEntry Tag="cmap" Offset="0x00001f2c" Length="0x0000133e" Checksum="0xc1c13a73" CodeFriendlyTag="cmap">
<Report ErrorType="I" ErrorCode="I0041" Message="Table not selected for validation" />
</TableEntry>
<TableEntry Tag="cvt " Offset="0x0000725c" Length="0x000007c4" Checksum="0xf34dda81" CodeFriendlyTag="cvt_">
<Report ErrorType="I" ErrorCode="I0041" Message="Table not selected for validation" />
</TableEntry>
<TableEntry Tag="fpgm" Offset="0x00006ce8" Length="0x00000573" Checksum="0x3775a72f" CodeFriendlyTag="fpgm">
<Report ErrorType="I" ErrorCode="I0041" Message="Table not selected for validation" />
</TableEntry>
<TableEntry Tag="gasp" Offset="0x00000250" Length="0x00000010" Checksum="0x00180009" CodeFriendlyTag="gasp">
<Report ErrorType="I" ErrorCode="I0041" Message="Table not selected for validation" />
</TableEntry>
<TableEntry Tag="glyf" Offset="0x00010ae8" Length="0x00039f8e" Checksum="0x2bf4ba66" CodeFriendlyTag="glyf">
<Report ErrorType="I" ErrorCode="I0041" Message="Table not selected for validation" />
</TableEntry>
<TableEntry Tag="hdmx" Offset="0x00008ec0" Length="0x00007c28" Checksum="0x11e0a83b" CodeFriendlyTag="hdmx">
<Report ErrorType="I" ErrorCode="I0041" Message="Table not selected for validation" />
</TableEntry>
<TableEntry Tag="head" Offset="0x0000017c" Length="0x00000036" Checksum="0xcafced47" CodeFriendlyTag="head">
<Report ErrorType="I" ErrorCode="I0041" Message="Table not selected for validation" />
</TableEntry>
<TableEntry Tag="hhea" Offset="0x000001b4" Length="0x00000024" Checksum="0x132911c0" CodeFriendlyTag="hhea">
<Report ErrorType="I" ErrorCode="I0041" Message="Table not selected for validation" />
</TableEntry>
<TableEntry Tag="hmtx" Offset="0x00007a20" Length="0x000014a0" Checksum="0x6d8332fd" CodeFriendlyTag="hmtx">
<Report ErrorType="I" ErrorCode="I0041" Message="Table not selected for validation" />
</TableEntry>
<TableEntry Tag="kern" Offset="0x0004dcb4" Length="0x00001464" Checksum="0xa677acd1" CodeFriendlyTag="kern">
<Report ErrorType="I" ErrorCode="I0041" Message="Table not selected for validation" />
</TableEntry>
<TableEntry Tag="loca" Offset="0x0000326c" Length="0x000014a4" Checksum="0x0aaafe10" CodeFriendlyTag="loca">
<Report ErrorType="I" ErrorCode="I0041" Message="Table not selected for validation" />
</TableEntry>
<TableEntry Tag="maxp" Offset="0x000001d8" Length="0x00000020" Checksum="0x0b8b10ac" CodeFriendlyTag="maxp">
<Report ErrorType="I" ErrorCode="I0041" Message="Table not selected for validation" />
</TableEntry>
<TableEntry Tag="name" Offset="0x00000260" Length="0x00001cc9" Checksum="0xff37ba10" CodeFriendlyTag="name">
<Report ErrorType="I" ErrorCode="I0041" Message="Table not selected for validation" />
</TableEntry>
<TableEntry Tag="post" Offset="0x0004aa78" Length="0x0000323b" Checksum="0xd6484739" CodeFriendlyTag="post">
<Report ErrorType="I" ErrorCode="I0041" Message="Table not selected for validation" />
</TableEntry>
<TableEntry Tag="prep" Offset="0x00005dd0" Length="0x00000f18" Checksum="0xd2662bf4" CodeFriendlyTag="prep">
<Report ErrorType="I" ErrorCode="I0041" Message="Table not selected for validation" />
</TableEntry>
<RasterizationTest_BW>
<Report ErrorType="E" ErrorCode="E6053" Message="Value exceeds capacity of 2 byte number" Details="Size 10, SFvFS, Glyph ID 132, At ByteOffset 652, In function 28 offsetted by 7" />
<Report ErrorType="E" ErrorCode="E6053" Message="Value exceeds capacity of 2 byte number" Details="Size 10, SFvFS, Glyph ID 400, At ByteOffset 662, In function 29 offsetted by 7" />
</RasterizationTest_BW>
<RasterizationTest_Grayscale>
<Report ErrorType="I" ErrorCode="I0052" Message="Rasterization not selected for validation" />
</RasterizationTest_Grayscale>
<RasterizationTest_ClearType>
<Report ErrorType="I" ErrorCode="I0052" Message="Rasterization not selected for validation" />
</RasterizationTest_ClearType>
</Font>
<Report ErrorType="I" ErrorCode="I0005" Message="Total time validating file" Details="0:00:00" />
</FontFile>
</FontValidatorReport>
