<?xml version="1.0" encoding="utf-8"?>
<?xml-stylesheet type="text/xsl" href="fval.xsl"?>
<FontValidatorReport RunDateTime="11 July 2016 05:54" MachineName="localhost">
<FontFile FileName="pyrite.ttf" FileNameAndPath="Z:/usr/share/fonts/larabie/uncommon/pyrite.ttf">
<Report ErrorType="I" ErrorCode="I0004" Message="The file begins with an Offset Table (file contains a single font)" />
<Font FontIndex="0">
<FontInfo FontName="Pyrite" FontVersion="Macromedia Fontographer 4.1 1/26/98" FontDate="26/01/1998" />
<Report ErrorType="P" ErrorCode="P0011" Message="The numTables field is non-zero" Details="15" TestName="_OFFSET_numTables" />
<Report ErrorType="E" ErrorCode="E0014" Message="The searchRange field is invalid" Details="48" TestName="_OFFSET_BinarySearchFields" />
<Report ErrorType="E" ErrorCode="E0013" Message="The rangeShift field is invalid" Details="192" TestName="_OFFSET_BinarySearchFields" />
<Report ErrorType="P" ErrorCode="P0032" Message="The directory entry tags are in ascending order" />
<Report ErrorType="P" ErrorCode="P0031" Message="The directory entry tag names are valid" />
<Report ErrorType="P" ErrorCode="P0030" Message="The directory entry table offsets are all multiples of 4" />
<Report ErrorType="P" ErrorCode="P0020" Message="All required tables are present" />
<Report ErrorType="W" ErrorCode="W0022" Message="Recommended table is missing" Details="gasp" />
<Report ErrorType="W" ErrorCode="W0022" Message="Recommended table is missing" Details="kern" />
<Report ErrorType="W" ErrorCode="W0022" Message="Recommended table is missing" Details="VDMX" />
<Report ErrorType="W" ErrorCode="W0022" Message="Recommended table is missing" Details="DSIG" />
<Report ErrorType="W" ErrorCode="W0021" Message="Table is unnecessary" Details="PCLT table not needed, Microsoft no longer recommends including this table" />
<Report ErrorType="W" ErrorCode="W0020" Message="Tables are not in optimal order" Details="table 'OS/2' precedes table 'head'" />
<TableEntry Tag="OS/2" Offset="0x0000715c" Length="0x00000056" Checksum="0x51e37a9f" CodeFriendlyTag="OS_2">
<Report ErrorType="I" ErrorCode="I0041" Message="Table not selected for validation" />
</TableEntry>
<TableEntry Tag="PCLT" Offset="0x000071b4" Length="0x00000036" Checksum="0x40c08a43" CodeFriendlyTag="PCLT">
<Report ErrorType="I" ErrorCode="I0041" Message="Table not selected for validation" />
</TableEntry>
<TableEntry Tag="cmap" Offset="0x0000546c" Length="0x00000728" Checksum="0xd7f0db33" CodeFriendlyTag="cmap">
<Report ErrorType="I" ErrorCode="I0041" Message="Table not selected for validation" />
</TableEntry>
<TableEntry Tag="cvt " Offset="0x00000404" Length="0x00000024" Checksum="0xb643bb57" CodeFriendlyTag="cvt_">
<Report ErrorType="I" ErrorCode="I0041" Message="Table not selected for validation" />
</TableEntry>
<TableEntry Tag="fpgm" Offset="0x000003f0" Length="0x00000014" Checksum="0x8333c24f" CodeFriendlyTag="fpgm">
<Report ErrorType="I" ErrorCode="I0041" Message="Table not selected for validation" />
</TableEntry>
<TableEntry Tag="glyf" Offset="0x00000470" Length="0x00003e8a" Checksum="0x6f728f9e" CodeFriendlyTag="glyf">
<Report ErrorType="I" ErrorCode="I0041" Message="Table not selected for validation" />
</TableEntry>
<TableEntry Tag="hdmx" Offset="0x00005b94" Length="0x000015c8" Checksum="0xa6795131" CodeFriendlyTag="hdmx">
<Report ErrorType="I" ErrorCode="I0041" Message="Table not selected for validation" />
</TableEntry>
<TableEntry Tag="head" Offset="0x000071ec" Length="0x00000036" Checksum="0xc40ad651" CodeFriendlyTag="head">
<Report ErrorType="I" ErrorCode="I0041" Message="Table not selected for validation" />
</TableEntry>
<TableEntry Tag="hhea" Offset="0x00007224" Length="0x00000024" Checksum="0x065603c0" CodeFriendlyTag="hhea">
<Report ErrorType="I" ErrorCode="I0041" Message="Table not selected for validation" />
</TableEntry>
<TableEntry Tag="hmtx" Offset="0x00004860" Length="0x00000560" Checksum="0xd2e11ec8" CodeFriendlyTag="hmtx">
<Report ErrorType="I" ErrorCode="I0041" Message="Table not selected for validation" />
</TableEntry>
<TableEntry Tag="loca" Offset="0x000042fc" Length="0x00000564" Checksum="0x003e5660" CodeFriendlyTag="loca">
<Report ErrorType="I" ErrorCode="I0041" Message="Table not selected for validation" />
</TableEntry>
<TableEntry Tag="maxp" Offset="0x00007248" Length="0x00000020" Checksum="0x01ff01ae" CodeFriendlyTag="maxp">
<Report ErrorType="I" ErrorCode="I0041" Message="Table not selected for validation" />
</TableEntry>
<TableEntry Tag="name" Offset="0x000000fc" Length="0x000002f1" Checksum="0x0ddfc26d" CodeFriendlyTag="name">
<Report ErrorType="I" ErrorCode="I0041" Message="Table not selected for validation" />
</TableEntry>
<TableEntry Tag="post" Offset="0x00004dc0" Length="0x000006a9" Checksum="0x3a8ce963" CodeFriendlyTag="post">
<Report ErrorType="I" ErrorCode="I0041" Message="Table not selected for validation" />
</TableEntry>
<TableEntry Tag="prep" Offset="0x00000428" Length="0x00000048" Checksum="0xc90fd213" CodeFriendlyTag="prep">
<Report ErrorType="I" ErrorCode="I0041" Message="Table not selected for validation" />
</TableEntry>
<RasterizationTest_BW>
<Report ErrorType="W" ErrorCode="W6010" Message="Projection and freedom vectors at or near perpendicular" Details="Size 10, MDAP[nrd], Glyph ID 9, At ByteOffset 62, " />
<Report ErrorType="W" ErrorCode="W6010" Message="Projection and freedom vectors at or near perpendicular" Details="Size 10, MDAP[nrd], Glyph ID 10, At ByteOffset 62, " />
<Report ErrorType="W" ErrorCode="W6010" Message="Projection and freedom vectors at or near perpendicular" Details="Size 10, MDAP[nrd], Glyph ID 17, At ByteOffset 96, " />
<Report ErrorType="W" ErrorCode="W6010" Message="Projection and freedom vectors at or near perpendicular" Details="Size 10, MDAP[nrd], Glyph ID 34, At ByteOffset 64, " />
<Report ErrorType="W" ErrorCode="W6010" Message="Projection and freedom vectors at or near perpendicular" Details="Size 10, MDAP[nrd], Glyph ID 38, At ByteOffset 76, " />
<Report ErrorType="W" ErrorCode="W6010" Message="Projection and freedom vectors at or near perpendicular" Details="Size 10, MDAP[nrd], Glyph ID 42, At ByteOffset 89, " />
<Report ErrorType="W" ErrorCode="W6010" Message="Projection and freedom vectors at or near perpendicular" Details="Size 10, MDAP[nrd], Glyph ID 46, At ByteOffset 96, " />
<Report ErrorType="W" ErrorCode="W6010" Message="Projection and freedom vectors at or near perpendicular" Details="Size 10, MDAP[nrd], Glyph ID 48, At ByteOffset 176, " />
<Report ErrorType="W" ErrorCode="W6010" Message="Projection and freedom vectors at or near perpendicular" Details="Size 10, MDAP[nrd], Glyph ID 48, At ByteOffset 198, " />
<Report ErrorType="W" ErrorCode="W6010" Message="Projection and freedom vectors at or near perpendicular" Details="Size 10, MDAP[nrd], Glyph ID 55, At ByteOffset 115, " />
<Report ErrorType="W" ErrorCode="W6010" Message="Projection and freedom vectors at or near perpendicular" Details="Size 10, MDAP[nrd], Glyph ID 58, At ByteOffset 62, " />
<Report ErrorType="W" ErrorCode="W6010" Message="Projection and freedom vectors at or near perpendicular" Details="Size 10, MDAP[nrd], Glyph ID 60, At ByteOffset 62, " />
<Report ErrorType="W" ErrorCode="W6010" Message="Projection and freedom vectors at or near perpendicular" Details="Size 10, MDAP[nrd], Glyph ID 65, At ByteOffset 64, " />
<Report ErrorType="W" ErrorCode="W6010" Message="Projection and freedom vectors at or near perpendicular" Details="Size 10, MDAP[nrd], Glyph ID 69, At ByteOffset 76, " />
<Report ErrorType="W" ErrorCode="W6010" Message="Projection and freedom vectors at or near perpendicular" Details="Size 10, MDAP[nrd], Glyph ID 73, At ByteOffset 89, " />
<Report ErrorType="W" ErrorCode="W6010" Message="Projection and freedom vectors at or near perpendicular" Details="Size 10, MDAP[nrd], Glyph ID 77, At ByteOffset 96, " />
<Report ErrorType="W" ErrorCode="W6010" Message="Projection and freedom vectors at or near perpendicular" Details="Size 10, MDAP[nrd], Glyph ID 79, At ByteOffset 176, " />
<Report ErrorType="W" ErrorCode="W6010" Message="Projection and freedom vectors at or near perpendicular" Details="Size 10, MDAP[nrd], Glyph ID 79, At ByteOffset 198, " />
<Report ErrorType="W" ErrorCode="W6010" Message="Projection and freedom vectors at or near perpendicular" Details="Size 10, MDAP[nrd], Glyph ID 86, At ByteOffset 115, " />
<Report ErrorType="W" ErrorCode="W6010" Message="Projection and freedom vectors at or near perpendicular" Details="Size 10, MDAP[nrd], Glyph ID 89, At ByteOffset 62, " />
<Report ErrorType="W" ErrorCode="W6010" Message="Projection and freedom vectors at or near perpendicular" Details="Size 10, MDAP[nrd], Glyph ID 91, At ByteOffset 62, " />
<Report ErrorType="W" ErrorCode="W6010" Message="Projection and freedom vectors at or near perpendicular" Details="Size 10, MDAP[nrd], Glyph ID 93, At ByteOffset 84, " />
<Report ErrorType="W" ErrorCode="W6010" Message="Projection and freedom vectors at or near perpendicular" Details="Size 10, MDAP[nrd], Glyph ID 100, At ByteOffset 84, " />
<Report ErrorType="W" ErrorCode="W6010" Message="Projection and freedom vectors at or near perpendicular" Details="Size 10, MDAP[nrd], Glyph ID 130, At ByteOffset 64, " />
<Report ErrorType="W" ErrorCode="W6010" Message="Projection and freedom vectors at or near perpendicular" Details="Size 10, MDAP[nrd], Glyph ID 139, At ByteOffset 95, " />
<Report ErrorType="W" ErrorCode="W6010" Message="Projection and freedom vectors at or near perpendicular" Details="Size 10, MDAP[nrd], Glyph ID 141, At ByteOffset 96, " />
<Report ErrorType="W" ErrorCode="W6010" Message="Projection and freedom vectors at or near perpendicular" Details="Size 10, MDAP[nrd], Glyph ID 142, At ByteOffset 96, " />
<Report ErrorType="W" ErrorCode="W6010" Message="Projection and freedom vectors at or near perpendicular" Details="Size 10, MDAP[nrd], Glyph ID 143, At ByteOffset 96, " />
<Report ErrorType="W" ErrorCode="W6010" Message="Projection and freedom vectors at or near perpendicular" Details="Size 10, MDAP[nrd], Glyph ID 144, At ByteOffset 96, " />
<Report ErrorType="W" ErrorCode="W6010" Message="Projection and freedom vectors at or near perpendicular" Details="Size 10, MDAP[nrd], Glyph ID 145, At ByteOffset 96, " />
<Report ErrorType="W" ErrorCode="W6010" Message="Projection and freedom vectors at or near perpendicular" Details="Size 10, MDAP[nrd], Glyph ID 146, At ByteOffset 100, " />
<Report ErrorType="W" ErrorCode="W6010" Message="Projection and freedom vectors at or near perpendicular" Details="Size 10, MDAP[nrd], Glyph ID 147, At ByteOffset 96, " />
<Report ErrorType="W" ErrorCode="W6010" Message="Projection and freedom vectors at or near perpendicular" Details="Size 10, MDAP[nrd], Glyph ID 162, At ByteOffset 64, " />
<Report ErrorType="W" ErrorCode="W6010" Message="Projection and freedom vectors at or near perpendicular" Details="Size 10, MDAP[nrd], Glyph ID 171, At ByteOffset 95, " />
<Report ErrorType="W" ErrorCode="W6010" Message="Projection and freedom vectors at or near perpendicular" Details="Size 10, MDAP[nrd], Glyph ID 173, At ByteOffset 96, " />
<Report ErrorType="W" ErrorCode="W6010" Message="Projection and freedom vectors at or near perpendicular" Details="Size 10, MDAP[nrd], Glyph ID 174, At ByteOffset 96, " />
<Report ErrorType="W" ErrorCode="W6010" Message="Projection and freedom vectors at or near perpendicular" Details="Size 10, MDAP[nrd], Glyph ID 175, At ByteOffset 96, " />
<Report ErrorType="W" ErrorCode="W6010" Message="Projection and freedom vectors at or near perpendicular" Details="Size 10, MDAP[nrd], Glyph ID 176, At ByteOffset 96, " />
<Report ErrorType="W" ErrorCode="W6010" Message="Projection and freedom vectors at or near perpendicular" Details="Size 10, MDAP[nrd], Glyph ID 177, At ByteOffset 96, " />
<Report ErrorType="W" ErrorCode="W6010" Message="Projection and freedom vectors at or near perpendicular" Details="Size 10, MDAP[nrd], Glyph ID 179, At ByteOffset 96, " />
<Report ErrorType="W" ErrorCode="W6010" Message="Projection and freedom vectors at or near perpendicular" Details="Size 10, MDAP[nrd], Glyph ID 269, At ByteOffset 96, " />
<Report ErrorType="W" ErrorCode="W6010" Message="Projection and freedom vectors at or near perpendicular" Details="Size 10, MDAP[nrd], Glyph ID 270, At ByteOffset 96, " />
</RasterizationTest_BW>
<RasterizationTest_Grayscale>
<Report ErrorType="I" ErrorCode="I0052" Message="Rasterization not selected for validation" />
</RasterizationTest_Grayscale>
<RasterizationTest_ClearType>
<Report ErrorType="I" ErrorCode="I0052" Message="Rasterization not selected for validation" />
</RasterizationTest_ClearType>
</Font>
<Report ErrorType="I" ErrorCode="I0005" Message="Total time validating file" Details="0:00:00" />
</FontFile>
</FontValidatorReport>
