<?xml version="1.0" encoding="utf-8"?>
<?xml-stylesheet type="text/xsl" href="fval.xsl"?>
<FontValidatorReport RunDateTime="17 July 2016 23:52" MachineName="localhost.localdomain">
<FontFile FileName="SpecialElite.ttf" FileNameAndPath="/usr/share/fonts/specialelite/SpecialElite.ttf">
<Report ErrorType="I" ErrorCode="I0004" Message="The file begins with an Offset Table (file contains a single font)" />
<Font FontIndex="0">
<FontInfo FontName="Special Elite" FontVersion="Version 1.000" FontDate="14/04/2011" />
<Report ErrorType="P" ErrorCode="P0011" Message="The numTables field is non-zero" Details="17" TestName="_OFFSET_numTables" />
<Report ErrorType="P" ErrorCode="P0010" Message="The searchRange, entrySelector, and rangeShift fields are all valid" TestName="_OFFSET_BinarySearchFields" />
<Report ErrorType="P" ErrorCode="P0032" Message="The directory entry tags are in ascending order" />
<Report ErrorType="P" ErrorCode="P0031" Message="The directory entry tag names are valid" />
<Report ErrorType="P" ErrorCode="P0030" Message="The directory entry table offsets are all multiples of 4" />
<Report ErrorType="P" ErrorCode="P0020" Message="All required tables are present" />
<Report ErrorType="W" ErrorCode="W0022" Message="Recommended table is missing" Details="hdmx" />
<Report ErrorType="W" ErrorCode="W0022" Message="Recommended table is missing" Details="VDMX" />
<Report ErrorType="W" ErrorCode="W0022" Message="Recommended table is missing" Details="DSIG" />
<Report ErrorType="P" ErrorCode="P0022" Message="No unnecessary tables are present" />
<Report ErrorType="P" ErrorCode="P0021" Message="Tables are in optimal order" />
<TableEntry Tag="GPOS" Offset="0x00028260" Length="0x00003048" Checksum="0x285be43d" CodeFriendlyTag="GPOS">
<Report ErrorType="I" ErrorCode="I0041" Message="Table not selected for validation" />
</TableEntry>
<TableEntry Tag="GSUB" Offset="0x0002b2a8" Length="0x000002f6" Checksum="0x9609b485" CodeFriendlyTag="GSUB">
<Report ErrorType="I" ErrorCode="I0041" Message="Table not selected for validation" />
</TableEntry>
<TableEntry Tag="OS/2" Offset="0x00000198" Length="0x00000060" Checksum="0x5f323103" CodeFriendlyTag="OS_2">
<Report ErrorType="I" ErrorCode="I0041" Message="Table not selected for validation" />
</TableEntry>
<TableEntry Tag="cmap" Offset="0x000007c0" Length="0x0000052a" Checksum="0xcee541a1" CodeFriendlyTag="cmap">
<Report ErrorType="I" ErrorCode="I0041" Message="Table not selected for validation" />
</TableEntry>
<TableEntry Tag="cvt " Offset="0x00000e58" Length="0x00000002" Checksum="0x002a0000" CodeFriendlyTag="cvt_">
<Report ErrorType="I" ErrorCode="I0041" Message="Table not selected for validation" />
</TableEntry>
<TableEntry Tag="fpgm" Offset="0x00000cec" Length="0x00000161" Checksum="0x9241dafa" CodeFriendlyTag="fpgm">
<Report ErrorType="I" ErrorCode="I0041" Message="Table not selected for validation" />
</TableEntry>
<TableEntry Tag="gasp" Offset="0x00028250" Length="0x00000010" Checksum="0x00170009" CodeFriendlyTag="gasp">
<Report ErrorType="I" ErrorCode="I0041" Message="Table not selected for validation" />
</TableEntry>
<TableEntry Tag="glyf" Offset="0x00001428" Length="0x0002034c" Checksum="0xe67b5f5e" CodeFriendlyTag="glyf">
<Report ErrorType="I" ErrorCode="I0041" Message="Table not selected for validation" />
</TableEntry>
<TableEntry Tag="head" Offset="0x0000011c" Length="0x00000036" Checksum="0xfade3888" CodeFriendlyTag="head">
<Report ErrorType="I" ErrorCode="I0041" Message="Table not selected for validation" />
</TableEntry>
<TableEntry Tag="hhea" Offset="0x00000154" Length="0x00000024" Checksum="0x0dcb0752" CodeFriendlyTag="hhea">
<Report ErrorType="I" ErrorCode="I0041" Message="Table not selected for validation" />
</TableEntry>
<TableEntry Tag="hmtx" Offset="0x000001f8" Length="0x000005c8" Checksum="0x6c705936" CodeFriendlyTag="hmtx">
<Report ErrorType="I" ErrorCode="I0041" Message="Table not selected for validation" />
</TableEntry>
<TableEntry Tag="kern" Offset="0x00021774" Length="0x00003012" Checksum="0x6a5e726f" CodeFriendlyTag="kern">
<Report ErrorType="I" ErrorCode="I0041" Message="Table not selected for validation" />
</TableEntry>
<TableEntry Tag="loca" Offset="0x00000e5c" Length="0x000005cc" Checksum="0x01e4cc14" CodeFriendlyTag="loca">
<Report ErrorType="I" ErrorCode="I0041" Message="Table not selected for validation" />
</TableEntry>
<TableEntry Tag="maxp" Offset="0x00000178" Length="0x00000020" Checksum="0x038c05d4" CodeFriendlyTag="maxp">
<Report ErrorType="I" ErrorCode="I0041" Message="Table not selected for validation" />
</TableEntry>
<TableEntry Tag="name" Offset="0x00024788" Length="0x0000333f" Checksum="0x7dbc5039" CodeFriendlyTag="name">
<Report ErrorType="I" ErrorCode="I0041" Message="Table not selected for validation" />
</TableEntry>
<TableEntry Tag="post" Offset="0x00027ac8" Length="0x00000786" Checksum="0x38d0fcfc" CodeFriendlyTag="post">
<Report ErrorType="I" ErrorCode="I0041" Message="Table not selected for validation" />
</TableEntry>
<TableEntry Tag="prep" Offset="0x00000e50" Length="0x00000007" Checksum="0x68068c85" CodeFriendlyTag="prep">
<Report ErrorType="I" ErrorCode="I0041" Message="Table not selected for validation" />
</TableEntry>
<RasterizationTest_BW>
<Report ErrorType="P" ErrorCode="P6000" Message="No problems were found during rasterization testing" />
</RasterizationTest_BW>
<RasterizationTest_Grayscale>
<Report ErrorType="I" ErrorCode="I0052" Message="Rasterization not selected for validation" />
</RasterizationTest_Grayscale>
<RasterizationTest_ClearType>
<Report ErrorType="I" ErrorCode="I0052" Message="Rasterization not selected for validation" />
</RasterizationTest_ClearType>
</Font>
<Report ErrorType="I" ErrorCode="I0005" Message="Total time validating file" Details="0:00:00" />
</FontFile>
</FontValidatorReport>
