<?xml version="1.0" encoding="utf-8"?>
<?xml-stylesheet type="text/xsl" href="fval.xsl"?>
<FontValidatorReport RunDateTime="29 October 2020 16:47" MachineName="localhost">
<FontFile FileName="IBMPlexMono-Light.otf" FileNameAndPath="/usr/share/fonts/ibm-plex/IBMPlexMono-Light.otf">
<Report ErrorType="I" ErrorCode="I0004" Message="The file begins with an Offset Table (file contains a single font)" />
<Font FontIndex="0">
<FontInfo FontName="IBM Plex Mono Light" FontVersion="Version 2.000" FontDate="22/12/2017" />
<Report ErrorType="P" ErrorCode="P0011" Message="The numTables field is non-zero" Details="12" TestName="_OFFSET_numTables" />
<Report ErrorType="P" ErrorCode="P0010" Message="The searchRange, entrySelector, and rangeShift fields are all valid" TestName="_OFFSET_BinarySearchFields" />
<Report ErrorType="P" ErrorCode="P0032" Message="The directory entry tags are in ascending order" />
<Report ErrorType="P" ErrorCode="P0031" Message="The directory entry tag names are valid" />
<Report ErrorType="P" ErrorCode="P0030" Message="The directory entry table offsets are all multiples of 4" />
<Report ErrorType="P" ErrorCode="P0020" Message="All required tables are present" />
<Report ErrorType="W" ErrorCode="W0022" Message="Recommended table is missing" Details="DSIG" />
<Report ErrorType="P" ErrorCode="P0022" Message="No unnecessary tables are present" />
<Report ErrorType="P" ErrorCode="P0021" Message="Tables are in optimal order" />
<TableEntry Tag="CFF " Offset="0x00001594" Length="0x0000c2b8" Checksum="0xfee84cb8" CodeFriendlyTag="CFF_">
<Report ErrorType="I" ErrorCode="I0041" Message="Table not selected for validation" />
</TableEntry>
<TableEntry Tag="GDEF" Offset="0x0000d84c" Length="0x00000082" Checksum="0x1b2d1b10" CodeFriendlyTag="GDEF">
<Report ErrorType="I" ErrorCode="I0041" Message="Table not selected for validation" />
</TableEntry>
<TableEntry Tag="GPOS" Offset="0x0000d8d0" Length="0x00000524" Checksum="0x1abd5ccf" CodeFriendlyTag="GPOS">
<Report ErrorType="I" ErrorCode="I0041" Message="Table not selected for validation" />
</TableEntry>
<TableEntry Tag="GSUB" Offset="0x0000ddf4" Length="0x000009ba" Checksum="0x2e957ed0" CodeFriendlyTag="GSUB">
<Report ErrorType="I" ErrorCode="I0041" Message="Table not selected for validation" />
</TableEntry>
<TableEntry Tag="OS/2" Offset="0x00000130" Length="0x00000060" Checksum="0x8bb66815" CodeFriendlyTag="OS_2">
<Report ErrorType="I" ErrorCode="I0041" Message="Table not selected for validation" />
</TableEntry>
<TableEntry Tag="cmap" Offset="0x00000b1c" Length="0x00000a56" Checksum="0xa4b013fd" CodeFriendlyTag="cmap">
<Report ErrorType="I" ErrorCode="I0041" Message="Table not selected for validation" />
</TableEntry>
<TableEntry Tag="head" Offset="0x000000cc" Length="0x00000036" Checksum="0x0d570a9b" CodeFriendlyTag="head">
<Report ErrorType="I" ErrorCode="I0041" Message="Table not selected for validation" />
</TableEntry>
<TableEntry Tag="hhea" Offset="0x00000104" Length="0x00000024" Checksum="0x057d039e" CodeFriendlyTag="hhea">
<Report ErrorType="I" ErrorCode="I0041" Message="Table not selected for validation" />
</TableEntry>
<TableEntry Tag="hmtx" Offset="0x0000e7b0" Length="0x00000d44" Checksum="0x57e1e8fa" CodeFriendlyTag="hmtx">
<Report ErrorType="I" ErrorCode="I0041" Message="Table not selected for validation" />
</TableEntry>
<TableEntry Tag="maxp" Offset="0x00000128" Length="0x00000006" Checksum="0x03525000" CodeFriendlyTag="maxp">
<Report ErrorType="I" ErrorCode="I0041" Message="Table not selected for validation" />
</TableEntry>
<TableEntry Tag="name" Offset="0x00000190" Length="0x00000989" Checksum="0xdbd45813" CodeFriendlyTag="name">
<Report ErrorType="I" ErrorCode="I0041" Message="Table not selected for validation" />
</TableEntry>
<TableEntry Tag="post" Offset="0x00001574" Length="0x00000020" Checksum="0xff66002c" CodeFriendlyTag="post">
<Report ErrorType="I" ErrorCode="I0041" Message="Table not selected for validation" />
</TableEntry>
<RasterizationTest_BW>
<Report ErrorType="I" ErrorCode="I6059" Message="Could not perform rasterization" Details="Font has PostScript outlines, rasterization not yet implemented" />
</RasterizationTest_BW>
<RasterizationTest_Grayscale>
<Report ErrorType="I" ErrorCode="I0052" Message="Rasterization not selected for validation" />
</RasterizationTest_Grayscale>
<RasterizationTest_ClearType>
<Report ErrorType="I" ErrorCode="I0052" Message="Rasterization not selected for validation" />
</RasterizationTest_ClearType>
</Font>
<Report ErrorType="I" ErrorCode="I0005" Message="Total time validating file" Details="0:00:00" />
</FontFile>
</FontValidatorReport>
