<?xml version="1.0" encoding="utf-8"?>
<?xml-stylesheet type="text/xsl" href="fval.xsl"?>
<FontValidatorReport RunDateTime="11 September 2019 18:36" MachineName="hintak-System-Product-Name">
<FontFile FileName="scritzy.ttf" FileNameAndPath="//usr/share/fonts/truetype/larabie/scritzy.ttf">
<Report ErrorType="I" ErrorCode="I0004" Message="The file begins with an Offset Table (file contains a single font)" />
<Font FontIndex="0">
<FontInfo FontName="Scritzy Regular" FontVersion="1.0 Wed Feb 14 22:37:06 1996" FontDate="14/02/1930" />
<Report ErrorType="P" ErrorCode="P0011" Message="The numTables field is non-zero" Details="15" TestName="_OFFSET_numTables" />
<Report ErrorType="E" ErrorCode="E0014" Message="The searchRange field is invalid" Details="48" TestName="_OFFSET_BinarySearchFields" />
<Report ErrorType="E" ErrorCode="E0013" Message="The rangeShift field is invalid" Details="192" TestName="_OFFSET_BinarySearchFields" />
<Report ErrorType="P" ErrorCode="P0032" Message="The directory entry tags are in ascending order" />
<Report ErrorType="P" ErrorCode="P0031" Message="The directory entry tag names are valid" />
<Report ErrorType="P" ErrorCode="P0030" Message="The directory entry table offsets are all multiples of 4" />
<Report ErrorType="P" ErrorCode="P0020" Message="All required tables are present" />
<Report ErrorType="W" ErrorCode="W0022" Message="Recommended table is missing" Details="gasp" />
<Report ErrorType="W" ErrorCode="W0022" Message="Recommended table is missing" Details="kern" />
<Report ErrorType="W" ErrorCode="W0022" Message="Recommended table is missing" Details="VDMX" />
<Report ErrorType="W" ErrorCode="W0022" Message="Recommended table is missing" Details="DSIG" />
<Report ErrorType="W" ErrorCode="W0021" Message="Table is unnecessary" Details="PCLT table not needed, Microsoft no longer recommends including this table" />
<Report ErrorType="W" ErrorCode="W0020" Message="Tables are not in optimal order" Details="table 'hmtx' precedes table 'OS/2'" />
<Report ErrorType="E" ErrorCode="E0030" Message="Directory Entry checksum error" Details="table 'OS/2', calc: 0x82a74d72, font: 0x784781a8" />
<TableEntry Tag="OS/2" Offset="0x00008574" Length="0x0000004e" Checksum="0x784781a8" CodeFriendlyTag="OS_2">
<Report ErrorType="I" ErrorCode="I0041" Message="Table not selected for validation" />
</TableEntry>
<Report ErrorType="E" ErrorCode="E0030" Message="Directory Entry checksum error" Details="table 'PCLT', calc: 0x94cdfecf, font: 0x62714617" />
<TableEntry Tag="PCLT" Offset="0x000085c4" Length="0x00000036" Checksum="0x62714617" CodeFriendlyTag="PCLT">
<Report ErrorType="I" ErrorCode="I0041" Message="Table not selected for validation" />
</TableEntry>
<Report ErrorType="E" ErrorCode="E0030" Message="Directory Entry checksum error" Details="table 'cmap', calc: 0xf5ba3afc, font: 0xc90b947d" />
<TableEntry Tag="cmap" Offset="0x000081b8" Length="0x0000021c" Checksum="0xc90b947d" CodeFriendlyTag="cmap">
<Report ErrorType="I" ErrorCode="I0041" Message="Table not selected for validation" />
</TableEntry>
<Report ErrorType="E" ErrorCode="E0030" Message="Directory Entry checksum error" Details="table 'cvt ', calc: 0x10150827, font: 0x082a1013" />
<TableEntry Tag="cvt " Offset="0x0000852c" Length="0x00000046" Checksum="0x082a1013" CodeFriendlyTag="cvt_">
<Report ErrorType="I" ErrorCode="I0041" Message="Table not selected for validation" />
</TableEntry>
<Report ErrorType="E" ErrorCode="E0030" Message="Directory Entry checksum error" Details="table 'fpgm', calc: 0xa7d95e93, font: 0x985cdca2" />
<TableEntry Tag="fpgm" Offset="0x00000430" Length="0x00000064" Checksum="0x985cdca2" CodeFriendlyTag="fpgm">
<Report ErrorType="I" ErrorCode="I0041" Message="Table not selected for validation" />
</TableEntry>
<Report ErrorType="E" ErrorCode="E0030" Message="Directory Entry checksum error" Details="table 'glyf', calc: 0x78140c3a, font: 0xaf9096f2" />
<TableEntry Tag="glyf" Offset="0x00000518" Length="0x00007a74" Checksum="0xaf9096f2" CodeFriendlyTag="glyf">
<Report ErrorType="I" ErrorCode="I0041" Message="Table not selected for validation" />
</TableEntry>
<Report ErrorType="E" ErrorCode="E0030" Message="Directory Entry checksum error" Details="table 'hdmx', calc: 0x13c6c6b3, font: 0x57d7c95e" />
<TableEntry Tag="hdmx" Offset="0x000085fc" Length="0x00000588" Checksum="0x57d7c95e" CodeFriendlyTag="hdmx">
<Report ErrorType="I" ErrorCode="I0041" Message="Table not selected for validation" />
</TableEntry>
<Report ErrorType="E" ErrorCode="E0030" Message="Directory Entry checksum error" Details="table 'head', calc: 0xc60197d6, font: 0xc7749663" />
<TableEntry Tag="head" Offset="0x000000fc" Length="0x00000036" Checksum="0xc7749663" CodeFriendlyTag="head">
<Report ErrorType="I" ErrorCode="I0041" Message="Table not selected for validation" />
</TableEntry>
<Report ErrorType="E" ErrorCode="E0030" Message="Directory Entry checksum error" Details="table 'hhea', calc: 0x07cb0398, font: 0x039a07c8" />
<TableEntry Tag="hhea" Offset="0x00000134" Length="0x00000024" Checksum="0x039a07c8" CodeFriendlyTag="hhea">
<Report ErrorType="I" ErrorCode="I0041" Message="Table not selected for validation" />
</TableEntry>
<Report ErrorType="E" ErrorCode="E0030" Message="Directory Entry checksum error" Details="table 'hmtx', calc: 0xc34709ba, font: 0x09bac334" />
<TableEntry Tag="hmtx" Offset="0x000083d4" Length="0x00000158" Checksum="0x09bac334" CodeFriendlyTag="hmtx">
<Report ErrorType="I" ErrorCode="I0041" Message="Table not selected for validation" />
</TableEntry>
<TableEntry Tag="loca" Offset="0x00007f8c" Length="0x0000015c" Checksum="0x00122946" CodeFriendlyTag="loca">
<Report ErrorType="I" ErrorCode="I0041" Message="Table not selected for validation" />
</TableEntry>
<Report ErrorType="E" ErrorCode="E0030" Message="Directory Entry checksum error" Details="table 'maxp', calc: 0x0130026c, font: 0x026d012f" />
<TableEntry Tag="maxp" Offset="0x00000158" Length="0x00000020" Checksum="0x026d012f" CodeFriendlyTag="maxp">
<Report ErrorType="I" ErrorCode="I0041" Message="Table not selected for validation" />
</TableEntry>
<Report ErrorType="E" ErrorCode="E0030" Message="Directory Entry checksum error" Details="table 'name', calc: 0x6959d8f9, font: 0xa16e1274" />
<TableEntry Tag="name" Offset="0x00000178" Length="0x000002b8" Checksum="0xa16e1274" CodeFriendlyTag="name">
<Report ErrorType="I" ErrorCode="I0041" Message="Table not selected for validation" />
</TableEntry>
<Report ErrorType="E" ErrorCode="E0030" Message="Directory Entry checksum error" Details="table 'post', calc: 0x07be07d3, font: 0x07d607bc" />
<TableEntry Tag="post" Offset="0x000080e8" Length="0x000000ce" Checksum="0x07d607bc" CodeFriendlyTag="post">
<Report ErrorType="I" ErrorCode="I0041" Message="Table not selected for validation" />
</TableEntry>
<Report ErrorType="E" ErrorCode="E0030" Message="Directory Entry checksum error" Details="table 'prep', calc: 0xf576ae08, font: 0x0fae76ef" />
<TableEntry Tag="prep" Offset="0x00000494" Length="0x00000083" Checksum="0x0fae76ef" CodeFriendlyTag="prep">
<Report ErrorType="I" ErrorCode="I0041" Message="Table not selected for validation" />
</TableEntry>
<RasterizationTest_BW>
<Report ErrorType="E" ErrorCode="E6053" Message="Value exceeds capacity of 2 byte number" Details="Size 10, SFVFS, Glyph ID 9, At ByteOffset 50" />
<Report ErrorType="E" ErrorCode="E6053" Message="Value exceeds capacity of 2 byte number" Details="Size 10, SFVFS, Glyph ID 14, At ByteOffset 55" />
<Report ErrorType="E" ErrorCode="E6053" Message="Value exceeds capacity of 2 byte number" Details="Size 10, SFVFS, Glyph ID 26, At ByteOffset 201" />
<Report ErrorType="E" ErrorCode="E6053" Message="Value exceeds capacity of 2 byte number" Details="Size 10, SFVFS, Glyph ID 26, At ByteOffset 201" />
<Report ErrorType="E" ErrorCode="E6053" Message="Value exceeds capacity of 2 byte number" Details="Size 10, SFVFS, Glyph ID 35, At ByteOffset 136" />
<Report ErrorType="E" ErrorCode="E6053" Message="Value exceeds capacity of 2 byte number" Details="Size 10, SFVFS, Glyph ID 35, At ByteOffset 149" />
<Report ErrorType="E" ErrorCode="E6053" Message="Value exceeds capacity of 2 byte number" Details="Size 10, SFVFS, Glyph ID 35, At ByteOffset 149" />
<Report ErrorType="E" ErrorCode="E6053" Message="Value exceeds capacity of 2 byte number" Details="Size 10, SFVFS, Glyph ID 40, At ByteOffset 67" />
<Report ErrorType="E" ErrorCode="E6053" Message="Value exceeds capacity of 2 byte number" Details="Size 10, SFVFS, Glyph ID 40, At ByteOffset 67" />
<Report ErrorType="E" ErrorCode="E6053" Message="Value exceeds capacity of 2 byte number" Details="Size 10, SFVFS, Glyph ID 54, At ByteOffset 168" />
<Report ErrorType="E" ErrorCode="E6053" Message="Value exceeds capacity of 2 byte number" Details="Size 10, SFVFS, Glyph ID 54, At ByteOffset 168" />
</RasterizationTest_BW>
<RasterizationTest_Grayscale>
<Report ErrorType="I" ErrorCode="I0052" Message="Rasterization not selected for validation" />
</RasterizationTest_Grayscale>
<RasterizationTest_ClearType>
<Report ErrorType="I" ErrorCode="I0052" Message="Rasterization not selected for validation" />
</RasterizationTest_ClearType>
</Font>
<Report ErrorType="I" ErrorCode="I0005" Message="Total time validating file" Details="0:00:00" />
</FontFile>
</FontValidatorReport>
