<?xml version="1.0" encoding="utf-8"?>
<?xml-stylesheet type="text/xsl" href="fval.xsl"?>
<FontValidatorReport RunDateTime="16 September 2019 15:20" MachineName="hintak-System-P">
<FontFile FileName="punknova-slanted.otf" FileNameAndPath="z://usr/share/texlive/texmf-dist/fonts/opentype/public/punknova/punknova-slanted.otf">
<Report ErrorType="I" ErrorCode="I0004" Message="The file begins with an Offset Table (file contains a single font)" />
<Font FontIndex="0">
<FontInfo FontName="Punk Nova Slanted" FontVersion="Version 001.003 " FontDate="22/11/2011" />
<Report ErrorType="P" ErrorCode="P0011" Message="The numTables field is non-zero" Details="12" TestName="_OFFSET_numTables" />
<Report ErrorType="P" ErrorCode="P0010" Message="The searchRange, entrySelector, and rangeShift fields are all valid" TestName="_OFFSET_BinarySearchFields" />
<Report ErrorType="P" ErrorCode="P0032" Message="The directory entry tags are in ascending order" />
<Report ErrorType="P" ErrorCode="P0031" Message="The directory entry tag names are valid" />
<Report ErrorType="P" ErrorCode="P0030" Message="The directory entry table offsets are all multiples of 4" />
<Report ErrorType="P" ErrorCode="P0020" Message="All required tables are present" />
<Report ErrorType="W" ErrorCode="W0022" Message="Recommended table is missing" Details="DSIG" />
<Report ErrorType="P" ErrorCode="P0022" Message="No unnecessary tables are present" />
<Report ErrorType="P" ErrorCode="P0021" Message="Tables are in optimal order" />
<TableEntry Tag="CFF " Offset="0x000008b0" Length="0x0003e41c" Checksum="0x19761aa3" CodeFriendlyTag="CFF_">
<Report ErrorType="I" ErrorCode="I0041" Message="Table not selected for validation" />
</TableEntry>
<TableEntry Tag="FFTM" Offset="0x000673c4" Length="0x0000001c" Checksum="0x5f6c4947" CodeFriendlyTag="FFTM">
<Report ErrorType="I" ErrorCode="I0040" Message="Not an OpenType table, contents not validated" Details="" />
</TableEntry>
<TableEntry Tag="GPOS" Offset="0x000400a8" Length="0x0002731c" Checksum="0x11eb6bb7" CodeFriendlyTag="GPOS">
<Report ErrorType="I" ErrorCode="I0041" Message="Table not selected for validation" />
</TableEntry>
<TableEntry Tag="GSUB" Offset="0x0003eccc" Length="0x000013dc" Checksum="0x32e67f6b" CodeFriendlyTag="GSUB">
<Report ErrorType="I" ErrorCode="I0041" Message="Table not selected for validation" />
</TableEntry>
<TableEntry Tag="OS/2" Offset="0x00000130" Length="0x00000060" Checksum="0x5a6d01f8" CodeFriendlyTag="OS_2">
<Report ErrorType="I" ErrorCode="I0041" Message="Table not selected for validation" />
</TableEntry>
<TableEntry Tag="cmap" Offset="0x00000694" Length="0x000001fa" Checksum="0x557bcb2b" CodeFriendlyTag="cmap">
<Report ErrorType="I" ErrorCode="I0041" Message="Table not selected for validation" />
</TableEntry>
<TableEntry Tag="head" Offset="0x000000cc" Length="0x00000036" Checksum="0xf7e31e49" CodeFriendlyTag="head">
<Report ErrorType="I" ErrorCode="I0041" Message="Table not selected for validation" />
</TableEntry>
<TableEntry Tag="hhea" Offset="0x00000104" Length="0x00000024" Checksum="0x06c10a1e" CodeFriendlyTag="hhea">
<Report ErrorType="I" ErrorCode="I0041" Message="Table not selected for validation" />
</TableEntry>
<TableEntry Tag="hmtx" Offset="0x000673e0" Length="0x0000219c" Checksum="0x18a09a07" CodeFriendlyTag="hmtx">
<Report ErrorType="I" ErrorCode="I0041" Message="Table not selected for validation" />
</TableEntry>
<TableEntry Tag="maxp" Offset="0x00000128" Length="0x00000006" Checksum="0x08675000" CodeFriendlyTag="maxp">
<Report ErrorType="I" ErrorCode="I0041" Message="Table not selected for validation" />
</TableEntry>
<TableEntry Tag="name" Offset="0x00000190" Length="0x00000501" Checksum="0x5a549152" CodeFriendlyTag="name">
<Report ErrorType="I" ErrorCode="I0041" Message="Table not selected for validation" />
</TableEntry>
<TableEntry Tag="post" Offset="0x00000890" Length="0x00000020" Checksum="0xff860032" CodeFriendlyTag="post">
<Report ErrorType="I" ErrorCode="I0041" Message="Table not selected for validation" />
</TableEntry>
<RasterizationTest_BW>
<Report ErrorType="I" ErrorCode="I6059" Message="Could not perform rasterization" Details="Font has PostScript outlines, rasterization not yet implemented" />
</RasterizationTest_BW>
<RasterizationTest_Grayscale>
<Report ErrorType="I" ErrorCode="I0052" Message="Rasterization not selected for validation" />
</RasterizationTest_Grayscale>
<RasterizationTest_ClearType>
<Report ErrorType="I" ErrorCode="I0052" Message="Rasterization not selected for validation" />
</RasterizationTest_ClearType>
</Font>
<Report ErrorType="I" ErrorCode="I0005" Message="Total time validating file" Details="0:00:00" />
</FontFile>
</FontValidatorReport>
